Metadata-Version: 2.1
Name: MyPackageAadi
Version: 0.1
Summary: Thiss is my first package
Home-page: UNKNOWN
Author: Aadi Tripathi
License: UNKNOWN
Platform: UNKNOWN
